examples/__init__.py
examples/caverphone_one_usage.py
examples/caverphone_two_usage.py
examples/editex_usage.py
examples/levenshtein_usage.py
examples/soundex_usage.py
examples/typox_usage.py
spellwise/__init__.py
spellwise/dictionary.py
spellwise/utils.py
spellwise/algorithms/__init__.py
spellwise/algorithms/base.py
spellwise/algorithms/caverphone_one.py
spellwise/algorithms/caverphone_two.py
spellwise/algorithms/editex.py
spellwise/algorithms/levenshtein.py
spellwise/algorithms/soundex.py
spellwise/algorithms/typox.py
spellwise-0.8.1.dist-info/LICENSE
spellwise-0.8.1.dist-info/METADATA
spellwise-0.8.1.dist-info/WHEEL
spellwise-0.8.1.dist-info/top_level.txt
spellwise-0.8.1.dist-info/RECORD
